LICENSE
setup.py
macvoice_utils/__init__.py
macvoice_utils.egg-info/PKG-INFO
macvoice_utils.egg-info/SOURCES.txt
macvoice_utils.egg-info/dependency_links.txt
macvoice_utils.egg-info/requires.txt
macvoice_utils.egg-info/top_level.txt